Workbook

Sheet Prezzi 2025
A1: Prezzi medi di acquisto 2025 - €/UM
A2: fonte: fatture passive - estrazione L. Trentin
A5: Materia prima | B5: UM | C5: gennaio | D5: febbraio | E5: marzo | F5: aprile | G5: maggio | H5: giugno | I5: luglio | J5: agosto | K5: settembre | L5: ottobre | M5: novembre | N5: dicembre | O5: Media
A6: Farina tipo 0 W300 | B6: kg | C6: 0.4088 | D6: 0.4117 | E6: 0.4098 | F6: 0.4104 | G6: 0.418 | H6: 0.4177 | I6: 0.4152 | J6: 0.4181 | K6: 0.4076 | L6: 0.417 | M6: 0.419 | N6: 0.415 | O6: =AVERAGE(C6:N6)
A7: Farina tipo 00 | B7: kg | C7: 0.3942 | D7: 0.3944 | E7: 0.3973 | F7: 0.3941 | G7: 0.4005 | H7: 0.4028 | I7: 0.3958 | J7: 0.3942 | K7: 0.3994 | L7: 0.3998 | M7: 0.3998 | N7: 0.3962 | O7: =AVERAGE(C7:N7)
A8: Olio girasole alto oleico | B8: kg | C8: 1.2712 | D8: 1.2737 | E8: 1.2934 | F8: 1.2701 | G8: 1.29 | H8: 1.2817 | I8: 1.2997 | J8: 1.2807 | K8: 1.3021 | L8: 1.2929 | M8: 1.293 | N8: 1.2901 | O8: =AVERAGE(C8:N8)
A9: Burro 82% | B9: kg | C9: 5.871 | D9: 5.9118 | E9: 5.8829 | F9: 6.0435 | G9: 5.9965 | H9: 5.9519 | I9: 5.9625 | J9: 5.9474 | K9: 6.007 | L9: 5.9093 | M9: 5.9906 | N9: 6.0185 | O9: =AVERAGE(C9:N9)
A10: Zucchero | B10: kg | C10: 0.8323 | D10: 0.8233 | E10: 0.8171 | F10: 0.8167 | G10: 0.8239 | H10: 0.8124 | I10: 0.8104 | J10: 0.8199 | K10: 0.8108 | L10: 0.825 | M10: 0.8224 | N10: 0.8197 | O10: =AVERAGE(C10:N10)
A11: Lievito compresso | B11: kg | C11: 1.5857 | D11: 1.574 | E11: 1.5549 | F11: 1.5509 | G11: 1.5828 | H11: 1.5579 | I11: 1.5754 | J11: 1.5581 | K11: 1.5644 | L11: 1.5638 | M11: 1.5431 | N11: 1.585 | O11: =AVERAGE(C11:N11)
A12: Semi misti tostati | B12: kg | C12: 3.4776 | D12: 3.4665 | E12: 3.4709 | F12: 3.457 | G12: 3.457 | H12: 3.4434 | I12: 3.485 | J12: 3.5296 | K12: 3.4432 | L12: 3.4557 | M12: 3.4955 | N12: 3.4524 | O12: =AVERAGE(C12:N12)
A13: Sale marino | B13: kg | C13: 0.3087 | D13: 0.3154 | E13: 0.3136 | F13: 0.3152 | G13: 0.3151 | H13: 0.309 | I13: 0.3113 | J13: 0.3072 | K13: 0.314 | L13: 0.3151 | M13: 0.3152 | N13: 0.3113 | O13: =AVERAGE(C13:N13)
A14: Film MAP PP/EVOH | B14: kg | C14: 4.2492 | D14: 4.2193 | E14: 4.2376 | F14: 4.1862 | G14: 4.2329 | H14: 4.2058 | I14: 4.261 | J14: 4.2625 | K14: 4.2403 | L14: 4.1884 | M14: 4.1975 | N14: 4.194 | O14: =AVERAGE(C14:N14)
A15: Vaschette PP | B15: 1000 pz | C15: 39.1165 | D15: 38.5859 | E15: 39.0693 | F15: 38.4632 | G15: 39.071 | H15: 38.3242 | I15: 38.404 | J15: 39.0794 | K15: 39.1421 | L15: 38.8503 | M15: 38.7309 | N15: 38.2871 | O15: =AVERAGE(C15:N15)
A16: Cartone ondulato | B16: pz | C16: 0.2844 | D16: 0.2842 | E16: 0.2832 | F16: 0.2846 | G16: 0.2848 | H16: 0.2847 | I16: 0.2831 | J16: 0.2822 | K16: 0.2855 | L16: 0.2892 | M16: 0.2891 | N16: 0.2856 | O16: =AVERAGE(C16:N16)
A17: Azoto alimentare | B17: m3 | C17: 1.1932 | D17: 1.169 | E17: 1.1738 | F17: 1.1749 | G17: 1.1726 | H17: 1.1917 | I17: 1.173 | J17: 1.1833 | K17: 1.1732 | L17: 1.1797 | M17: 1.183 | N17: 1.1973 | O17: =AVERAGE(C17:N17)

Sheet Prezzi 2026
A1: Prezzi medi di acquisto 2026 - €/UM
A2: fonte: fatture passive - estrazione L. Trentin
A5: Materia prima | B5: UM | C5: gennaio | D5: febbraio | E5: marzo | F5: aprile | G5: maggio | H5: Media
A6: Farina tipo 0 W300 | B6: kg | C6: 0.412 | D6: 0.4165 | E6: 0.4211 | F6: 0.4256 | G6: 0.4301 | H6: =AVERAGE(C6:G6)
A7: Farina tipo 00 | B7: kg | C7: 0.398 | D7: 0.4024 | E7: 0.4068 | F7: 0.4111 | G7: 0.4155 | H7: =AVERAGE(C7:G7)
A8: Olio girasole alto oleico | B8: kg | C8: 1.279 | D8: 1.2794 | E8: 1.4432 | F8: 1.4261 | G8: 1.4397 | H8: =AVERAGE(C8:G8)
A9: Burro 82% | B9: kg | C9: 5.9253 | D9: 6.014 | E9: 6.0246 | F9: 6.0914 | G9: 5.976 | H9: =AVERAGE(C9:G9)
A10: Zucchero | B10: kg | C10: 0.8307 | D10: 0.8358 | E10: 0.8378 | F10: 0.8412 | G10: 0.832 | H10: =AVERAGE(C10:G10)
A11: Lievito compresso | B11: kg | C11: 1.5468 | D11: 1.5655 | E11: 1.5996 | F11: 1.5989 | G11: 1.6051 | H11: =AVERAGE(C11:G11)
A12: Semi misti tostati | B12: kg | C12: 3.4916 | D12: 3.5417 | E12: 3.5489 | F12: 3.5351 | G12: 3.4963 | H12: =AVERAGE(C12:G12)
A13: Sale marino | B13: kg | C13: 0.3111 | D13: 0.3124 | E13: 0.3136 | F13: 0.3159 | G13: 0.3119 | H13: =AVERAGE(C13:G13)
A14: Film MAP PP/EVOH | B14: kg | C14: 4.2706 | D14: 4.3097 | E14: 4.2495 | F14: 4.3249 | G14: 4.3376 | H14: =AVERAGE(C14:G14)
A15: Vaschette PP | B15: 1000 pz | C15: 39.0042 | D15: 38.3232 | E15: 38.9388 | F15: 38.9794 | G15: 38.7552 | H15: =AVERAGE(C15:G15)
A16: Cartone ondulato | B16: pz | C16: 0.2858 | D16: 0.2846 | E16: 0.2919 | F16: 0.2894 | G16: 0.2898 | H16: =AVERAGE(C16:G16)
A17: Azoto alimentare | B17: m3 | C17: 1.196 | D17: 1.1706 | E17: 1.1862 | F17: 1.1865 | G17: 1.2177 | H17: =AVERAGE(C17:G17)
A19: olio: +11% dichiarato dal fornitore da marzo (comunicazione via mail del 24/02)
A20: farina: prezzo indicizzato alla Borsa Merci di Bologna, revisione trimestrale da contratto

Sheet Delta
A1: Variazione prezzi 2026 vs media 2025
A5: Materia prima | B5: UM | C5: Media 2025 | D5: Media 2026 (5 mesi) | E5: Delta € | F5: Delta % | G5: Consumo annuo | H5: Impatto € anno | I5: Peso su costo MP | J5: Priorità
A6: Farina tipo 0 W300 | B6: kg | C6: ='Prezzi 2025'!O6 | D6: ='Prezzi 2026'!H6 | E6: =D6-C6 | F6: =E6/C6 | G6: 960000 | H6: =E6*G6 | I6: =H6/SUM($H$6:$H$17) | J6: =IF(F6>0.08,"ALTA",IF(F6>0.03,"media","bassa"))
A7: Farina tipo 00 | B7: kg | C7: ='Prezzi 2025'!O7 | D7: ='Prezzi 2026'!H7 | E7: =D7-C7 | F7: =E7/C7 | G7: 420000 | H7: =E7*G7 | I7: =H7/SUM($H$6:$H$17) | J7: =IF(F7>0.08,"ALTA",IF(F7>0.03,"media","bassa"))
A8: Olio girasole alto oleico | B8: kg | C8: ='Prezzi 2025'!O8 | D8: ='Prezzi 2026'!H8 | E8: =D8-C8 | F8: =E8/C8 | G8: 148000 | H8: =E8*G8 | I8: =H8/SUM($H$6:$H$17) | J8: =IF(F8>0.08,"ALTA",IF(F8>0.03,"media","bassa"))
A9: Burro 82% | B9: kg | C9: ='Prezzi 2025'!O9 | D9: ='Prezzi 2026'!H9 | E9: =D9-C9 | F9: =E9/C9 | G9: 96000 | H9: =E9*G9 | I9: =H9/SUM($H$6:$H$17) | J9: =IF(F9>0.08,"ALTA",IF(F9>0.03,"media","bassa"))
A10: Zucchero | B10: kg | C10: ='Prezzi 2025'!O10 | D10: ='Prezzi 2026'!H10 | E10: =D10-C10 | F10: =E10/C10 | G10: 88000 | H10: =E10*G10 | I10: =H10/SUM($H$6:$H$17) | J10: =IF(F10>0.08,"ALTA",IF(F10>0.03,"media","bassa"))
A11: Lievito compresso | B11: kg | C11: ='Prezzi 2025'!O11 | D11: ='Prezzi 2026'!H11 | E11: =D11-C11 | F11: =E11/C11 | G11: 24000 | H11: =E11*G11 | I11: =H11/SUM($H$6:$H$17) | J11: =IF(F11>0.08,"ALTA",IF(F11>0.03,"media","bassa"))
A12: Semi misti tostati | B12: kg | C12: ='Prezzi 2025'!O12 | D12: ='Prezzi 2026'!H12 | E12: =D12-C12 | F12: =E12/C12 | G12: 32000 | H12: =E12*G12 | I12: =H12/SUM($H$6:$H$17) | J12: =IF(F12>0.08,"ALTA",IF(F12>0.03,"media","bassa"))
A13: Sale marino | B13: kg | C13: ='Prezzi 2025'!O13 | D13: ='Prezzi 2026'!H13 | E13: =D13-C13 | F13: =E13/C13 | G13: 9600 | H13: =E13*G13 | I13: =H13/SUM($H$6:$H$17) | J13: =IF(F13>0.08,"ALTA",IF(F13>0.03,"media","bassa"))
A14: Film MAP PP/EVOH | B14: kg | C14: ='Prezzi 2025'!O14 | D14: ='Prezzi 2026'!H14 | E14: =D14-C14 | F14: =E14/C14 | G14: 54000 | H14: =E14*G14 | I14: =H14/SUM($H$6:$H$17) | J14: =IF(F14>0.08,"ALTA",IF(F14>0.03,"media","bassa"))
A15: Vaschette PP | B15: 1000 pz | C15: ='Prezzi 2025'!O15 | D15: ='Prezzi 2026'!H15 | E15: =D15-C15 | F15: =E15/C15 | G15: 3200 | H15: =E15*G15 | I15: =H15/SUM($H$6:$H$17) | J15: =IF(F15>0.08,"ALTA",IF(F15>0.03,"media","bassa"))
A16: Cartone ondulato | B16: pz | C16: ='Prezzi 2025'!O16 | D16: ='Prezzi 2026'!H16 | E16: =D16-C16 | F16: =E16/C16 | G16: 240000 | H16: =E16*G16 | I16: =H16/SUM($H$6:$H$17) | J16: =IF(F16>0.08,"ALTA",IF(F16>0.03,"media","bassa"))
A17: Azoto alimentare | B17: m3 | C17: ='Prezzi 2025'!O17 | D17: ='Prezzi 2026'!H17 | E17: =D17-C17 | F17: =E17/C17 | G17: 4800 | H17: =E17*G17 | I17: =H17/SUM($H$6:$H$17) | J17: =IF(F17>0.08,"ALTA",IF(F17>0.03,"media","bassa"))
A18: IMPATTO TOTALE A VOLUME COSTANTE | H18: =SUM(H6:H17)

Sheet Impatto a budget
A1: Impatto dell'aumento MP sul conto economico e sul prezzo di vendita
A5: Voce | B5: Valore | C5: Note
A6: Costo MP a budget 2026 | B6: =1284000*0.412 | C6: dal budget economico
A7: Impatto aumento prezzi | B7: =Delta!H18
A8: Costo MP rivisto | B8: =B6+B7
A9: Incidenza su fatturato budget | B9: =B8/13200000
A10: Aumento prezzo di vendita necessario a compensare | B10: =B7/13200000
A11: Aumento richiesto dal cliente (in senso opposto) | B11: -0.045 | C11: richiesta buyer Tosano del 05/05/2026
A12: Forbice complessiva da recuperare | B12: =B10-B11
A14: (L.T.) mettere questo foglio davanti a Rossi alla prossima riunione. I numeri parlano da soli.
A15: (G.B.) NO. Non si fanno vedere i costi al cliente. MAI.
