Workbook

Sheet Incassi
A1: Previsionale di cassa giugno - agosto 2026
A2: L. Trentin - rev. 3 del 05/06/2026 - le settimane in rosso vanno oltre l'affidamento
A5: Settimana | B5: Dal | C5: Al | D5: Cliente | E5: Rif. fatture | F5: Scadenza reale | G5: Importo | H5: Probabilità | I5: Atteso | J5: Note
A6: W23 | B6: 01/06/2026 | C6: 07/06/2026 | D6: Tosano Cerea SpA | E6: 2026/188-189-190 | F6: 05/06/2026 | G6: 148920.4 | H6: 1 | I6: =G6*H6 | J6: fatture di marzo, 90 gg
A7: W23 | B7: 01/06/2026 | C7: 07/06/2026 | D7: Ho.Re.Ca. grossisti | E7: varie | F7: 03/06/2026 | G7: 8410 | H7: 0.9 | I7: =G7*H7
A8: W24 | B8: 08/06/2026 | C8: 14/06/2026 | D8: Alì SpA | E8: 2026/201-204 | F8: 10/06/2026 | G8: 31280.6 | H8: 1 | I8: =G8*H8
A9: W24 | B9: 08/06/2026 | C9: 14/06/2026 | D9: Rossetto Trade SpA | E9: 2026/198 | F9: 12/06/2026 | G9: 18940 | H9: 0.5 | I9: =G9*H9 | J9: contestata per il richiamo, probabile nota di credito
A10: W25 | B10: 15/06/2026 | C10: 21/06/2026 | D10: Famila Nordest | E10: 2026/210 | F10: 18/06/2026 | G10: 22150.8 | H10: 1 | I10: =G10*H10
A11: W26 | B11: 22/06/2026 | C11: 28/06/2026 | D11: Tosano Cerea SpA | E11: 2026/215-218 | F11: 26/06/2026 | G11: 96420 | H11: 0.95 | I11: =G11*H11 | J11: al netto sconto merce 2%
A12: W27 | B12: 29/06/2026 | C12: 05/07/2026 | D12: Alì SpA | E12: 2026/222 | F12: 02/07/2026 | G12: 27110.3 | H12: 1 | I12: =G12*H12
A13: W28 | B13: 06/07/2026 | C13: 12/07/2026 | D13: Tosano Cerea SpA | E13: 2026/230-231 | F13: 09/07/2026 | G13: 134780.2 | H13: 0.95 | I13: =G13*H13
A14: W29 | B14: 13/07/2026 | C14: 19/07/2026 | D14: varie minori | G14: 14200 | H14: 0.8 | I14: =G14*H14
A15: W30 | B15: 20/07/2026 | C15: 26/07/2026 | D15: Tosano Cerea SpA | E15: 2026/240 | F15: 24/07/2026 | G15: 88900 | H15: 0.95 | I15: =G15*H15
A16: W31 | B16: 27/07/2026 | C16: 02/08/2026 | D16: Famila Nordest | E16: 2026/244 | F16: 30/07/2026 | G16: 19870.4 | H16: 1 | I16: =G16*H16
A17: W32 | B17: 03/08/2026 | C17: 09/08/2026 | D17: Alì SpA | E17: 2026/250 | F17: 06/08/2026 | G17: 24310 | H17: 1 | I17: =G17*H17 | J17: agosto: incassi lenti, storicamente slittano
A18: W33 | B18: 10/08/2026 | C18: 16/08/2026 | D18: - | G18: 0 | H18: 0 | I18: =G18*H18 | J18: chiusura ferie
A19: W34 | B19: 17/08/2026 | C19: 23/08/2026 | D19: Tosano Cerea SpA | E19: 2026/255 | F19: 21/08/2026 | G19: 71200 | H19: 0.9 | I19: =G19*H19
D20: TOTALE ATTESO | I20: =SUM(I6:I19)

Sheet Pagamenti
A1: Uscite previste giugno - agosto 2026
A5: Settimana | B5: Beneficiario | C5: Causale | D5: Scadenza | E5: Importo | F5: Rinviabile | G5: Note
A6: W23 | B6: Molino Veneto SpA | C6: RIBA farine aprile | D6: 05/06/2026 | E6: 42180.6 | F6: no
A7: W23 | B7: Dipendenti | C7: Stipendi maggio | D7: 10/06/2026 | E7: 118400 | F7: no | G7: 50 dipendenti + straordinari domenicali
A8: W23 | B8: Erario | C8: F24 - IVA + ritenute | D8: 16/06/2026 | E8: 38920.4 | F8: no
A9: W24 | B9: Criotech Impianti Srl | C9: ACCONTO 30% ord. 2026/017 tunnel | D9: 12/06/2026 | E9: 87000 | F9: forse | G9: Fantin dice che se slitta perdiamo lo slot di consegna
A10: W24 | B10: Veneta Energia SpA | C10: Utenze maggio | D10: 14/06/2026 | E10: 21640.8 | F10: no
A11: W25 | B11: Flexipack Nordest Srl | C11: RIBA imballi | D11: 18/06/2026 | E11: 16220 | F11: no
A12: W25 | B12: Oleificio Adriatico SpA | C12: RIBA olio (prezzo +11%) | D12: 20/06/2026 | E12: 19880.5 | F12: sì | G12: hanno già sollecitato una volta
A13: W26 | B13: Leasing UniCredit | C13: Rata forno FT-02 | D13: 28/06/2026 | E13: 4180 | F13: no
A14: W26 | B14: CSQA Certificazioni Srl | C14: Saldo audit febbraio | D14: 30/06/2026 | E14: 6100 | F14: sì | G14: fattura ferma da marzo, hanno scritto due volte
A15: W27 | B15: Dipendenti | C15: Stipendi giugno | D15: 10/07/2026 | E15: 112800 | F15: no
A16: W27 | B16: Erario | C16: F24 | D16: 16/07/2026 | E16: 34110 | F16: no
A17: W28 | B17: Molino Veneto SpA | C17: RIBA farine maggio | D17: 09/07/2026 | E17: 39440.2 | F17: no
A18: W29 | B18: Analytica Veneta Srl | C18: Analisi urgenti reclamo | D18: 15/07/2026 | E18: 4820 | F18: sì | G18: fuori budget - costo non qualità
A19: W30 | B19: Criotech Impianti Srl | C19: SALDO 60% alla consegna | D19: 24/07/2026 | E19: 174000 | F19: no | G19: QUESTO È IL PROBLEMA
A20: W31 | B20: Dipendenti | C20: Stipendi luglio + 14esima | D20: 31/07/2026 | E20: 186200 | F20: no
A21: W32 | B21: Veneta Energia SpA | C21: Utenze luglio | D21: 06/08/2026 | E21: 18900 | F21: no
A22: W34 | B22: Assicurazioni | C22: Rinnovo RC prodotto | D22: 20/08/2026 | E22: 9420 | F22: no | G22: scadenza 30/06 prorogata
B23: TOTALE USCITE | E23: =SUM(E6:E22)

Sheet Saldo progressivo
A1: Saldo di conto corrente progressivo - UniCredit filiale Cologna Veneta
A2: affidamento c/c 250.000 € - anticipo fatture 400.000 € (utilizzato 212.000 al 31/05)
A5: Settimana | B5: Saldo iniziale | C5: Incassi | D5: Uscite | E5: Saldo finale | F5: Fido residuo | G5: Utilizzo anticipo | H5: Allarme
A6: W22 (attuale) | B6: 41820.6 | C6: 0 | D6: 0 | E6: =B6 | F6: =250000+E6 | G6: 212000
A7: W23 | B7: =E6 | C7: =SUMIF(Incassi!A:A,A7,Incassi!I:I) | D7: =SUMIF(Pagamenti!A:A,A7,Pagamenti!E:E) | E7: =B7+C7-D7 | F7: =250000+E7 | G7: =IF(E7<0,-E7,0) | H7: =IF(F7<0,"SCONFINAMENTO",IF(F7<40000,"tensione",""))
A8: W24 | B8: =E7 | C8: =SUMIF(Incassi!A:A,A8,Incassi!I:I) | D8: =SUMIF(Pagamenti!A:A,A8,Pagamenti!E:E) | E8: =B8+C8-D8 | F8: =250000+E8 | G8: =IF(E8<0,-E8,0) | H8: =IF(F8<0,"SCONFINAMENTO",IF(F8<40000,"tensione",""))
A9: W25 | B9: =E8 | C9: =SUMIF(Incassi!A:A,A9,Incassi!I:I) | D9: =SUMIF(Pagamenti!A:A,A9,Pagamenti!E:E) | E9: =B9+C9-D9 | F9: =250000+E9 | G9: =IF(E9<0,-E9,0) | H9: =IF(F9<0,"SCONFINAMENTO",IF(F9<40000,"tensione",""))
A10: W26 | B10: =E9 | C10: =SUMIF(Incassi!A:A,A10,Incassi!I:I) | D10: =SUMIF(Pagamenti!A:A,A10,Pagamenti!E:E) | E10: =B10+C10-D10 | F10: =250000+E10 | G10: =IF(E10<0,-E10,0) | H10: =IF(F10<0,"SCONFINAMENTO",IF(F10<40000,"tensione",""))
A11: W27 | B11: =E10 | C11: =SUMIF(Incassi!A:A,A11,Incassi!I:I) | D11: =SUMIF(Pagamenti!A:A,A11,Pagamenti!E:E) | E11: =B11+C11-D11 | F11: =250000+E11 | G11: =IF(E11<0,-E11,0) | H11: =IF(F11<0,"SCONFINAMENTO",IF(F11<40000,"tensione",""))
A12: W28 | B12: =E11 | C12: =SUMIF(Incassi!A:A,A12,Incassi!I:I) | D12: =SUMIF(Pagamenti!A:A,A12,Pagamenti!E:E) | E12: =B12+C12-D12 | F12: =250000+E12 | G12: =IF(E12<0,-E12,0) | H12: =IF(F12<0,"SCONFINAMENTO",IF(F12<40000,"tensione",""))
A13: W29 | B13: =E12 | C13: =SUMIF(Incassi!A:A,A13,Incassi!I:I) | D13: =SUMIF(Pagamenti!A:A,A13,Pagamenti!E:E) | E13: =B13+C13-D13 | F13: =250000+E13 | G13: =IF(E13<0,-E13,0) | H13: =IF(F13<0,"SCONFINAMENTO",IF(F13<40000,"tensione",""))
A14: W30 | B14: =E13 | C14: =SUMIF(Incassi!A:A,A14,Incassi!I:I) | D14: =SUMIF(Pagamenti!A:A,A14,Pagamenti!E:E) | E14: =B14+C14-D14 | F14: =250000+E14 | G14: =IF(E14<0,-E14,0) | H14: =IF(F14<0,"SCONFINAMENTO",IF(F14<40000,"tensione",""))
A15: W31 | B15: =E14 | C15: =SUMIF(Incassi!A:A,A15,Incassi!I:I) | D15: =SUMIF(Pagamenti!A:A,A15,Pagamenti!E:E) | E15: =B15+C15-D15 | F15: =250000+E15 | G15: =IF(E15<0,-E15,0) | H15: =IF(F15<0,"SCONFINAMENTO",IF(F15<40000,"tensione",""))
A16: W32 | B16: =E15 | C16: =SUMIF(Incassi!A:A,A16,Incassi!I:I) | D16: =SUMIF(Pagamenti!A:A,A16,Pagamenti!E:E) | E16: =B16+C16-D16 | F16: =250000+E16 | G16: =IF(E16<0,-E16,0) | H16: =IF(F16<0,"SCONFINAMENTO",IF(F16<40000,"tensione",""))
A17: W33 | B17: =E16 | C17: =SUMIF(Incassi!A:A,A17,Incassi!I:I) | D17: =SUMIF(Pagamenti!A:A,A17,Pagamenti!E:E) | E17: =B17+C17-D17 | F17: =250000+E17 | G17: =IF(E17<0,-E17,0) | H17: =IF(F17<0,"SCONFINAMENTO",IF(F17<40000,"tensione",""))
A18: W34 | B18: =E17 | C18: =SUMIF(Incassi!A:A,A18,Incassi!I:I) | D18: =SUMIF(Pagamenti!A:A,A18,Pagamenti!E:E) | E18: =B18+C18-D18 | F18: =250000+E18 | G18: =IF(E18<0,-E18,0) | H18: =IF(F18<0,"SCONFINAMENTO",IF(F18<40000,"tensione",""))
A20: (L.T.) se il Criotech va pagato in W24 e il Tosano slitta di una settimana, in W25 siamo fuori fido.
A21: (L.T.) chiesto a UniCredit ampliamento anticipo a 500.000. Risposta attesa entro il 20/06.
A22: (G.B. a penna sul foglio stampato) 'chiedere a Rossi se anticipa il pagamento in cambio di 1 punto'

Sheet Ipotesi
A1: Ipotesi alla base del previsionale
A4: 1. Tosano paga a 90 gg d.f.f.m. - storicamente slitta di 4-7 giorni oltre la scadenza teorica
A5: 2. Sconto merce 2% dedotto in fattura, contributo promo liquidato a fine anno (non in cassa qui)
A6: 3. Rossetto: prudenzialmente al 50% per la contestazione sul richiamo
A7: 4. Criotech: acconto 30% + saldo 60% alla consegna prevista fine luglio + 10% al collaudo (settembre)
A8: 5. Non è considerato il credito d'imposta 4.0 (compensabile solo dopo l'interconnessione - vedi nota Bellotto)
A9: 6. Non è considerato il costo del ritiro dei lotti L26130/L26131 stimato in 31.500 € (decisione sospesa)
A10: 7. Agosto: 3 settimane di chiusura, incassi storicamente in ritardo di 10 gg
A11: 8. Non sono considerati eventuali oneri per la contestazione sindacale sugli straordinari
A14: rischio principale: concentrazione su un solo cliente (vedi analisi marginalità)
A20: VERSIONE SUPERATA - fare riferimento al file senza (2) - L.T. 06/06
